{
    "id": 126011921,
    "name": "Limbo Easy",
    "author": "Antohi",
    "creators": ["Antohi"],
    "verifier": "Antohi",
    "verification": "https://youtu.be/NGqM5ajl9bA",
    "percentToQualify": "100",
    "password": "",
    "records": [
                 {
            "user": "Sklork",
            "link": "https://youtu.be/4m5pAKSAojI",
            "percent": 100,
            "hz": 240
        },
         {
            "user": "tyuu6ihn",
            "link": "https://youtu.be/jhxhE5wLE6s",
            "percent": 100,
            "hz": 240
        },
          {
            "user": "Syrup",
            "link": "https://www.youtube.com/watch?v=2vthPnW_V1g",
            "percent": 100,
            "hz": 240
        },
        {
            "user": "CelesteGD",
            "link": "https://youtu.be/sLoZ7DtOeII",
            "percent": 100,
            "hz": 240
        },
        {
            "user": "Toupeurvibreur",
            "link": "https://youtu.be/jfRoIXJEHB0",
            "percent": 100,
            "hz": 240
            }
    ]
}
