{
    "id": 132099626,
    "name": "Thoughtless",
    "author": "CelesteGD",
    "creators": ["CelesteGD"],
    "verifier": "CelesteGD",
    "verification": "https://youtu.be/sn8wuIeftk0",
    "percentToQualify": "100",
    "password": "",
    "records": [
        {
            "user": "Smilli",
            "link": "https://www.youtube.com/watch?v=E_LnI4pSuzc",
            "percent": 100,
            "hz": 240
        },
        {
            "user": "Toupeurvibreur",
            "link": "https://youtu.be/jfRoIXJEHB0",
            "percent": 100,
            "hz": 240
        }
    ]
}
